{
  "gitSyncId": "68d716f52765f94fabd3777f_1791e0de-ccee-4eba-9ed8-a7c58120ad6e",
  "id": "singup_JSObject1.btn_signInonClick",
  "pluginId": "js-plugin",
  "pluginType": "JS",
  "unpublishedAction": {
    "actionConfiguration": {
      "encodeParamsToggle": true,
      "jsArguments": [],
      "paginationType": "NONE",
      "timeoutInMillisecond": 10000
    },
    "clientSideExecution": true,
    "collectionId": "singup_JSObject1",
    "confirmBeforeExecute": false,
    "datasource": {
      "isAutoGenerated": false,
      "name": "UNUSED_DATASOURCE",
      "pluginId": "js-plugin"
    },
    "dynamicBindingPathList": [
      {
        "key": "body"
      }
    ],
    "fullyQualifiedName": "JSObject1.btn_signInonClick",
    "name": "btn_signInonClick",
    "pageId": "singup",
    "runBehaviour": "MANUAL",
    "userSetOnLoad": false
  }
}